hcli/__init__.py
hcli/main.py
hcli/api/__init__.py
hcli/api/utils.py
hcli/commands/__init__.py
hcli/commands/apps.py
hcli/commands/auth.py
hcli/commands/deploy.py
hcli/commands/machines.py
hcli/commands/organizations.py
hcli/commands/set.py
hcli/utils/__init__.py
hcli/utils/apps.py
hcli/utils/config.py
hcli/utils/machines.py
hcli/utils/permanent_storage.py
hcli/utils/permissions.py
hcli/utils/terminal/__init__.py
hcli/utils/terminal/prompt.py
hcli/utils/terminal/render.py
hcli-1.0.16.dist-info/METADATA
hcli-1.0.16.dist-info/WHEEL
hcli-1.0.16.dist-info/entry_points.txt
hcli-1.0.16.dist-info/top_level.txt
hcli-1.0.16.dist-info/RECORD
