Metadata-Version: 2.1
Name: hcli
Version: 1.0.16
Summary: Official CLI for huddu.io
Home-page: https://github.com/hudduapp/cli
Author: Joshua3212
Author-email: hello@huddu.io
License: MIT
Requires-Dist: typer
Requires-Dist: rich
Requires-Dist: huddu
Requires-Dist: inquirer
Requires-Dist: pyyaml
